ISS_Info/ISS_Info.py
ISS_Info/__init__.py
ISS_Info-1.0.0.dist-info/LICENSE.txt
ISS_Info-1.0.0.dist-info/METADATA
ISS_Info-1.0.0.dist-info/WHEEL
ISS_Info-1.0.0.dist-info/top_level.txt
ISS_Info-1.0.0.dist-info/RECORD
