Metadata-Version: 2.1
Name: ISS-Info
Version: 1.0.0
Summary: Python wrapper for tracking information about International Space Station via http://open-notify.org/
Home-page: https://github.com/Quarantine-Projects/ISS_Info
Author: Salil Gautam & Prakhar Dixit
License: MIT
Keywords: ISS,Space,Station,API
Platform: UNKNOWN
Classifier: Intended Audience :: Developers
Classifier: Topic :: Software Development :: Build Tools
Classifier: License :: OSI Approved :: MIT License
Classifier: Programming Language :: Python :: 3
Classifier: Programming Language :: Python :: 3.5
Classifier: Programming Language :: Python :: 3.6
Classifier: Programming Language :: Python :: 3.7
Classifier: Programming Language :: Python :: 3.8
Classifier: Operating System :: OS Independent
Requires-Python: >=3, !=3.0.*, !=3.1.*, !=3.2.*, !=3.3.*, !=3.4.*
Requires-Dist: requests (>=2.23.0)
